pyessent/__init__.py
pyessent/pyessent.py
PyEssent-0.14.dist-info/LICENSE
PyEssent-0.14.dist-info/METADATA
PyEssent-0.14.dist-info/WHEEL
PyEssent-0.14.dist-info/top_level.txt
PyEssent-0.14.dist-info/RECORD
