Metadata-Version: 2.1
Name: PyEssent
Version: 0.14
Summary: A wrapper around Essent's API
Home-page: UNKNOWN
Author: Sylvia van Os
Author-email: sylvia@hackerchick.me
License: Apache2
Platform: UNKNOWN
Requires-Dist: requests (>=2.22.0)
